simple_yt_api/__init__.py
simple_yt_api/exceptions.py
simple_yt_api/main.py
simple_yt_api/models.py
simple_yt_api/utils.py
simple_yt_api-4.0.0.dist-info/WHEEL
simple_yt_api-4.0.0.dist-info/METADATA
simple_yt_api-4.0.0.dist-info/RECORD
