Metadata-Version: 2.4
Name: simple-yt-api
Version: 4.0.0
Summary: A simple and easy-to-use unofficial YouTube API Wrapper.
Keywords: simple,unofficial,youtube,api,metadata,transcript,wrapper
Author: Ahmet Burhan Kayalı
Author-email: Ahmet Burhan Kayalı <ahmetburhan1703@gmail.com>
License-Expression: MIT
Classifier: Programming Language :: Python :: 3.10
Classifier: Programming Language :: Python :: 3.11
Classifier: Programming Language :: Python :: 3.12
Classifier: Programming Language :: Python :: 3.13
Classifier: Programming Language :: Python :: 3.14
Classifier: Intended Audience :: Developers
Classifier: Intended Audience :: Science/Research
Classifier: Topic :: Software Development :: Libraries :: Python Modules
Classifier: Topic :: Internet :: WWW/HTTP
Classifier: Topic :: Multimedia :: Video
Classifier: Topic :: Text Processing :: Markup :: HTML
Requires-Dist: requests>=2.32.5
Requires-Dist: beautifulsoup4>=4.14.3
Requires-Dist: youtube-transcript-api>=1.2.3
Requires-Python: >=3.10
Project-URL: Bug Tracker, https://github.com/SoAp9035/simple-yt-api/issues
Project-URL: Homepage, https://github.com/SoAp9035/simple-yt-api
